ohawf/__init__.py
ohawf/_modidx.py
ohawf/core.py
ohawf-23.0.10.dist-info/LICENSE
ohawf-23.0.10.dist-info/METADATA
ohawf-23.0.10.dist-info/WHEEL
ohawf-23.0.10.dist-info/entry_points.txt
ohawf-23.0.10.dist-info/top_level.txt
ohawf-23.0.10.dist-info/RECORD
