Metadata-Version: 2.1
Name: ohawf
Version: 23.0.10
Summary: Easy Google login from Jupyter Notebooks
Home-page: https://github.com/miklevin/ohawf
Author: Mike Levin
Author-email: miklevin@gmail.com
License: Apache Software License 2.0
Keywords: nbdev jupyter notebook python
Classifier: Development Status :: 4 - Beta
Classifier: Intended Audience :: Developers
Classifier: Natural Language :: English
Classifier: Programming Language :: Python :: 3.6
Classifier: Programming Language :: Python :: 3.7
Classifier: Programming Language :: Python :: 3.8
Classifier: Programming Language :: Python :: 3.9
Classifier: Programming Language :: Python :: 3.10
Classifier: License :: OSI Approved :: Apache Software License
Requires-Python: >=3.6
License-File: LICENSE
Requires-Dist: google-api-python-client
Requires-Dist: google-auth-oauthlib
Provides-Extra: dev
